dilator/__init__.py
dilator/__main__.py
png_dilator-0.8.2.dist-info/METADATA
png_dilator-0.8.2.dist-info/WHEEL
png_dilator-0.8.2.dist-info/entry_points.txt
png_dilator-0.8.2.dist-info/top_level.txt
png_dilator-0.8.2.dist-info/RECORD
