Metadata-Version: 2.1
Name: png-dilator
Version: 0.8.2
Summary: Dilate texture with low alpha pixel to prevent "black edge" when rendered by GL
Home-page: UNKNOWN
Author: GT
Author-email: caogtaa@gmail.com
License: MIT
Platform: UNKNOWN
Classifier: License :: OSI Approved :: MIT License
Classifier: Programming Language :: Python :: 3
Classifier: Programming Language :: Python :: 3.7
Requires-Dist: opencv-python
Requires-Dist: numpy
Requires-Dist: fire
